{
  "storage_version": 1,
  "name": "diy-gdo",
  "friendly_name": "DIY Garage Door Opener",
  "comment": null,
  "esphome_version": "2024.11.3",
  "src_version": 1,
  "address": "diy-gdo.local",
  "web_port": null,
  "esp_platform": "ESP32",
  "build_path": ".\\.esphome\\build\\diy-gdo",
  "firmware_bin_path": ".\\.esphome\\build\\diy-gdo\\.pioenvs\\diy-gdo\\firmware.bin",
  "loaded_integrations": [
    "api",
    "binary",
    "button",
    "captive_portal",
    "copy",
    "cover",
    "esp32",
    "esp32_ble",
    "esp32_ble_server",
    "esp32_improv",
    "esphome",
    "gpio",
    "improv_base",
    "improv_serial",
    "ledc",
    "light",
    "logger",
    "md5",
    "mdns",
    "network",
    "ota",
    "output",
    "preferences",
    "restart",
    "rtttl",
    "safe_mode",
    "script",
    "sensor",
    "socket",
    "status_led",
    "substitutions",
    "template",
    "text_sensor",
    "uptime",
    "version",
    "web_server_base",
    "web_server_idf",
    "wifi",
    "wifi_info",
    "wifi_signal"
  ],
  "no_mdns": false,
  "framework": "esp-idf",
  "core_platform": "esp32"
}
